AUTHORS.rst
CHANGES.rst
LICENSE
MANIFEST.in
README.rst
setup.cfg
setup.py
aioamqp/__init__.py
aioamqp/channel.py
aioamqp/compat.py
aioamqp/constants.py
aioamqp/envelope.py
aioamqp/exceptions.py
aioamqp/frame.py
aioamqp/properties.py
aioamqp/protocol.py
aioamqp/version.py
aioamqp_authentise.egg-info/PKG-INFO
aioamqp_authentise.egg-info/SOURCES.txt
aioamqp_authentise.egg-info/dependency_links.txt
aioamqp_authentise.egg-info/requires.txt
aioamqp_authentise.egg-info/top_level.txt
docs/Makefile
docs/api.rst
docs/changelog.rst
docs/conf.py
docs/index.rst
docs/introduction.rst
docs/examples/hello_world.rst
docs/examples/index.rst
docs/examples/publish_subscribe.rst
docs/examples/routing.rst
docs/examples/rpc.rst
docs/examples/topics.rst
docs/examples/work_queue.rst
examples/emit_log.py
examples/emit_log_direct.py
examples/emit_log_topic.py
examples/new_task.py
examples/receive.py
examples/receive_log.py
examples/receive_log_direct.py
examples/receive_log_topic.py
examples/rpc_client.py
examples/rpc_server.py
examples/send.py
examples/worker.py