Metadata-Version: 1.1
Name: aioamqp-authentise
Version: 0.10.0
Summary: AMQP implementation using asyncio
Home-page: https://github.com/Authentise/aioamqp
Author: Polyconseil dev' team, Authentise dev team
Author-email: opensource+aioamqp@polyconseil.fr
License: BSD
Download-URL: https://pypi.python.org/pypi/aioamqp
Platform: all
Classifier: Development Status :: 4 - Beta
Classifier: Intended Audience :: Developers
Classifier: License :: OSI Approved :: BSD License
Classifier: Operating System :: OS Independent
Classifier: Programming Language :: Python
Classifier: Programming Language :: Python :: 3
Classifier: Programming Language :: Python :: 3.5
Classifier: Programming Language :: Python :: 3.6
